LICENSE
MANIFEST.in
README.md
setup.cfg
setup.py
requirements/base.txt
requirements/development.txt
ridi_django_oauth2_resource/__init__.py
ridi_django_oauth2_resource/config.py
ridi_django_oauth2_resource/constants.py
ridi_django_oauth2_resource/decorators.py
ridi_django_oauth2_resource/exceptions.py
ridi_django_oauth2_resource/managers.py
ridi_django_oauth2_resource/middlewares.py
ridi_django_oauth2_resource/models.py
ridi_django_oauth2_resource/response.py
ridi_django_oauth2_resource.egg-info/PKG-INFO
ridi_django_oauth2_resource.egg-info/SOURCES.txt
ridi_django_oauth2_resource.egg-info/dependency_links.txt
ridi_django_oauth2_resource.egg-info/requires.txt
ridi_django_oauth2_resource.egg-info/top_level.txt
ridi_django_oauth2_resource/migrations/0001_initial.py
ridi_django_oauth2_resource/migrations/0002_auto_20180322_1157.py
ridi_django_oauth2_resource/migrations/__init__.py
ridi_django_oauth2_resource/utils/__init__.py
ridi_django_oauth2_resource/utils/cookie.py
ridi_django_oauth2_resource/utils/token.py
ridi_oauth2/__init__.py
ridi_oauth2/client/__init__.py
ridi_oauth2/client/constants.py
ridi_oauth2/client/dtos.py
ridi_oauth2/client/exceptions.py
ridi_oauth2/client/grant.py
ridi_oauth2/common/__init__.py
ridi_oauth2/common/constants.py
ridi_oauth2/common/utils/__init__.py
ridi_oauth2/common/utils/string.py
ridi_oauth2/introspector/__init__.py
ridi_oauth2/introspector/base.py
ridi_oauth2/introspector/dtos.py
ridi_oauth2/introspector/exceptions.py
ridi_oauth2/introspector/helpers.py
ridi_oauth2/introspector/jwt_introspector.py
ridi_oauth2/resource/__init__.py
ridi_oauth2/resource/constants.py
ridi_oauth2/resource/scope_checker.py